{
  "total": 2,
  "apps": [
    {
      "id": 92405,
      "name": "icp4",
      "desc": "",
      "domain": "",
      "status": "update_succ",
      "replicas": 1,
      "volumes": [],
      "spec_id": 10,
      "created_at": "2016-04-14T11:54:28Z",
      "updated_at": "2016-05-03T02:14:03Z",
      "public_ip": "106.2.36.81",
      "private_ip": null,
      "version_control": {
        "type": null,
        "path": null,
        "subdir": null,
        "branch": "master",
        "version": "",
        "account": "",
        "password": ""
      },
      "custom_docker_file": "",
      "image_id": 29047,
      "use_load_balance": 1,
      "load_balance": {
        "bandwidth": 1,
        "port_map": [
          {
            "protocol": "HTTP",
            "source_port": 80,
            "destination_port": 81
          }
        ],
        "charge_type": 1
      },
      "env_var": {
        "ENV": "PRODUCTION",
        "CONFIG_URL": "http://apollodev.nos.netease.com/146192995136214606349336371459339304947",
        "PORT": "81"
      },
      "web_hook_url": "https://open.c.163.com/api/v1/hooks/app/54e5fbfb1bc0492288abe6c98b7c2122"
    },
    {
      "id": 92399,
      "name": "icp2",
      "desc": "",
      "domain": "",
      "status": "update_succ",
      "replicas": 1,
      "volumes": [],
      "spec_id": 10,
      "created_at": "2016-04-14T11:53:33Z",
      "updated_at": "2016-05-03T02:14:05Z",
      "public_ip": "106.2.97.159",
      "private_ip": null,
      "version_control": {
        "type": null,
        "path": null,
        "subdir": null,
        "branch": "master",
        "version": "",
        "account": "",
        "password": ""
      },
      "custom_docker_file": "",
      "image_id": 29047,
      "use_load_balance": 1,
      "load_balance": {
        "bandwidth": 1,
        "port_map": [
          {
            "protocol": "HTTP",
            "source_port": 80,
            "destination_port": 81
          }
        ],
        "charge_type": 1
      },
      "env_var": {
        "CONFIG_URL": "http://apollodev.nos.netease.com/146192995136214606349336371459339304947",
        "PORT": "81",
        "ENV": "PRODUCTION"
      },
      "web_hook_url": "https://open.c.163.com/api/v1/hooks/app/5a560695727647cbb0a10eceb4964a40"
    }
  ]
}
